MANIFEST.in
README.rst
requirements.txt
setup.cfg
setup.py
kotti_survey/__init__.py
kotti_survey/__init__.pyc
kotti_survey/fanstatic.py
kotti_survey/fanstatic.pyc
kotti_survey/resources.py
kotti_survey/resources.pyc
kotti_survey.egg-info/PKG-INFO
kotti_survey.egg-info/SOURCES.txt
kotti_survey.egg-info/dependency_links.txt
kotti_survey.egg-info/entry_points.txt
kotti_survey.egg-info/not-zip-safe
kotti_survey.egg-info/requires.txt
kotti_survey.egg-info/top_level.txt
kotti_survey/alembic/README
kotti_survey/alembic/env.py
kotti_survey/alembic/env.pyc
kotti_survey/alembic/script.py.mako
kotti_survey/alembic/versions/.gitkeep
kotti_survey/alembic/versions/README.md
kotti_survey/locale/.gitkeep
kotti_survey/locale/README
kotti_survey/static/scripts.js
kotti_survey/static/scripts.min.js
kotti_survey/static/styles.css
kotti_survey/static/styles.min.css
kotti_survey/templates/answerview.pt
kotti_survey/templates/questionview.pt
kotti_survey/templates/respondents.pt
kotti_survey/templates/resultview.pt
kotti_survey/templates/surveyview.pt
kotti_survey/tests/conftest.py
kotti_survey/tests/test_functional.py
kotti_survey/tests/test_resources.py
kotti_survey/tests/test_view.py
kotti_survey/views/__init__.py
kotti_survey/views/__init__.pyc
kotti_survey/views/edit.py
kotti_survey/views/edit.pyc
kotti_survey/views/view.py
kotti_survey/views/view.pyc